ctffindplot/__init__.py
ctffindplot/__main__.py
ctffindplot/dash_app.py
ctffindplot/plot.py
ctffindplot/run.py
ctffindplot/watch.py
ctffindplot-0.0.7.dist-info/LICENSE.txt
ctffindplot-0.0.7.dist-info/METADATA
ctffindplot-0.0.7.dist-info/WHEEL
ctffindplot-0.0.7.dist-info/entry_points.txt
ctffindplot-0.0.7.dist-info/top_level.txt
ctffindplot-0.0.7.dist-info/RECORD
