Metadata-Version: 2.1
Name: ctffindplot
Version: 0.0.7
Summary: Sequentially plot ctffind results from aligned micrographs
Home-page: https://github.com/alberttxu/ctffindplot
Author: Albert Xu
Author-email: albert.t.xu@gmail.com
License: MIT
Platform: UNKNOWN
Classifier: Programming Language :: Python :: 3
Classifier: License :: OSI Approved :: MIT License
Classifier: Operating System :: OS Independent
Requires-Dist: PyGnuplot
Requires-Dist: dash
Requires-Dist: pandas
